AUTHORS.md
HISTORY.md
LICENSE
minos/api_gateway/discovery/__init__.py
minos/api_gateway/discovery/__main__.py
minos/api_gateway/discovery/cli.py
minos/api_gateway/discovery/database/__init__.py
minos/api_gateway/discovery/database/client.py
minos/api_gateway/discovery/domain/__init__.py
minos/api_gateway/discovery/domain/endpoint.py
minos/api_gateway/discovery/domain/exceptions.py
minos/api_gateway/discovery/domain/microservice.py
minos/api_gateway/discovery/exceptions.py
minos/api_gateway/discovery/health_status/__init__.py
minos/api_gateway/discovery/health_status/checkers.py
minos/api_gateway/discovery/health_status/services.py
minos/api_gateway/discovery/launchers.py
minos/api_gateway/discovery/service.py
minos/api_gateway/discovery/views/__init__.py
minos/api_gateway/discovery/views/endpoint.py
minos/api_gateway/discovery/views/endpoints.py
minos/api_gateway/discovery/views/microservice.py
minos/api_gateway/discovery/views/router.py
minos_discovery-0.1.1.dist-info/entry_points.txt
minos_discovery-0.1.1.dist-info/LICENSE
minos_discovery-0.1.1.dist-info/WHEEL
minos_discovery-0.1.1.dist-info/METADATA
minos_discovery-0.1.1.dist-info/RECORD
