Metadata-Version: 2.1
Name: minos-discovery
Version: 0.1.1
Summary: Minos Discovery service for Microservices subscription.
Home-page: https://clariteia.com
License: MIT
Keywords: clariteia,minos,api gateway,discovery
Author: Clariteia Devs
Author-email: devs@clariteia.com
Requires-Python: >=3.9,<4.0
Classifier: Development Status :: 2 - Pre-Alpha
Classifier: Intended Audience :: Developers
Classifier: License :: OSI Approved :: MIT License
Classifier: Natural Language :: English
Classifier: Programming Language :: Python :: 3
Classifier: Programming Language :: Python :: 3.9
Requires-Dist: aioredis (>=2.0.1,<3.0.0)
Requires-Dist: cached-property (>=1.5.2,<2.0.0)
Requires-Dist: minos-apigateway-common (>=0.0,<0.1)
Requires-Dist: typer (>=0.3.2,<0.4.0)
Project-URL: Repository, https://github.com/clariteia/discovery
